opep/__init__.py
opep/__version__.py
opep/cli.py
opep/peps/pep-0001.md
opep/peps/pep-0002.md
opep/peps/pep-0003.md
opep/peps/pep-0004.md
opep/peps/pep-0005.md
opep/peps/pep-0006.md
opep/peps/pep-0007.md
opep/peps/pep-0008.md
opep/peps/pep-0009.md
opep/peps/pep-0010.md
opep/peps/pep-0011.md
opep/peps/pep-0012.md
opep/peps/pep-0013.md
opep/peps/pep-0020.md
opep/peps/pep-0042.md
opep/peps/pep-0100.md
opep/peps/pep-0101.md
opep/peps/pep-0102.md
opep/peps/pep-0103.md
opep/peps/pep-0160.md
opep/peps/pep-0200.md
opep/peps/pep-0201.md
opep/peps/pep-0202.md
opep/peps/pep-0203.md
opep/peps/pep-0204.md
opep/peps/pep-0205.md
opep/peps/pep-0206.md
opep/peps/pep-0207.md
opep/peps/pep-0208.md
opep/peps/pep-0209.md
opep/peps/pep-0210.md
opep/peps/pep-0211.md
opep/peps/pep-0212.md
opep/peps/pep-0213.md
opep/peps/pep-0214.md
opep/peps/pep-0215.md
opep/peps/pep-0216.md
opep/peps/pep-0217.md
opep/peps/pep-0218.md
opep/peps/pep-0219.md
opep/peps/pep-0220.md
opep/peps/pep-0221.md
opep/peps/pep-0222.md
opep/peps/pep-0223.md
opep/peps/pep-0224.md
opep/peps/pep-0225.md
opep/peps/pep-0226.md
opep/peps/pep-0227.md
opep/peps/pep-0228.md
opep/peps/pep-0229.md
opep/peps/pep-0230.md
opep/peps/pep-0231.md
opep/peps/pep-0232.md
opep/peps/pep-0233.md
opep/peps/pep-0234.md
opep/peps/pep-0235.md
opep/peps/pep-0236.md
opep/peps/pep-0237.md
opep/peps/pep-0238.md
opep/peps/pep-0239.md
opep/peps/pep-0240.md
opep/peps/pep-0241.md
opep/peps/pep-0242.md
opep/peps/pep-0243.md
opep/peps/pep-0244.md
opep/peps/pep-0245.md
opep/peps/pep-0246.md
opep/peps/pep-0247.md
opep/peps/pep-0248.md
opep/peps/pep-0249.md
opep/peps/pep-0250.md
opep/peps/pep-0251.md
opep/peps/pep-0252.md
opep/peps/pep-0253.md
opep/peps/pep-0254.md
opep/peps/pep-0255.md
opep/peps/pep-0256.md
opep/peps/pep-0257.md
opep/peps/pep-0258.md
opep/peps/pep-0259.md
opep/peps/pep-0260.md
opep/peps/pep-0261.md
opep/peps/pep-0262.md
opep/peps/pep-0263.md
opep/peps/pep-0264.md
opep/peps/pep-0265.md
opep/peps/pep-0266.md
opep/peps/pep-0267.md
opep-2020.10.1.dist-info/LICENSE
opep-2020.10.1.dist-info/METADATA
opep-2020.10.1.dist-info/WHEEL
opep-2020.10.1.dist-info/entry_points.txt
opep-2020.10.1.dist-info/top_level.txt
opep-2020.10.1.dist-info/RECORD
