Metadata-Version: 2.1
Name: opep
Version: 2020.10.1
Summary: Open PEPs on your terminal.
Home-page: https://github.com/vinayak-mehta/opep
Author: Vinayak Mehta
Author-email: vmehta94@gmail.com
License: Apache 2.0
Platform: UNKNOWN
Classifier: License :: OSI Approved :: Apache Software License
Classifier: Programming Language :: Python :: 3.6
Classifier: Programming Language :: Python :: 3.7
Classifier: Programming Language :: Python :: 3.8
Requires-Dist: Click (>=7.0)
Requires-Dist: rich (==7.0.0)
Provides-Extra: dev
Requires-Dist: Click (>=7.0) ; extra == 'dev'
Requires-Dist: Sphinx (>=2.2.1) ; extra == 'dev'
Requires-Dist: rich (==7.0.0) ; extra == 'dev'
